Workbook
Name Timeline_Date_completed: #N/A
Name Timeline_Date_completed1: #N/A

Sheet Dashboard
B1: PERFORMANCE DASHBOARD
M26: Total num of WFs | Q26: =SUM(Total!I2:I4993) -> 4210
M31: WFs completed today | Q31: =VLOOKUP((TODAY()),Summary!A:B,2,FALSE) -> 17
M36: Average WFs per month | Q36: =Total!J2 -> 247.64706

Sheet Pivot
A2: MDG VS Make CRs | L2: Weekly total | O2: MDG process types | T2: Total WFs completed | X2: WEEKLY CRs COMPARISION
A3: Count of Change Request | B3: Column Labels | L3: Row Labels | M3: Count of Change Request | O3: Count of Change Request | P3: Column Labels | T3: Row Labels | U3: Count of Change Request | X3: Count of Change Request | Y3: Column Labels
A4: Row Labels | B4: Make | C4: Mass | D4: MDG | E4: Grand Total | L4: 46129 | M4: 25 | O4: Row Labels | P4: 2025 | Q4: Grand Total | T4: 2024 | X4: Row Labels | Y4: Make | Z4: Mass | AA4: MDG | AB4: Grand Total
A5: 2024 | D5: 10 | E5: 10 | L5: 46132 | M5: 25 | O5: Alpin | P5: 55 | Q5: 55 | T5: Dec | U5: 10 | X5: 2026
A6: 2025 | L6: 46133 | M6: 40 | O6: Customer master | P6: 27 | Q6: 27 | T6: 2025 | X6: 46129 | Y6: 3 | AA6: 22 | AB6: 25
A7: Jan | D7: 42 | E7: 42 | L7: 46134 | M7: 43 | O7: Deployment | P7: 408 | Q7: 408 | T7: Jan | U7: 42 | X7: 46132 | Y7: 2 | Z7: 2 | AA7: 21 | AB7: 25
A8: Feb | B8: 1 | D8: 54 | E8: 55 | L8: 46135 | M8: 40 | O8: DIR update | P8: 59 | Q8: 59 | T8: Feb | U8: 55 | X8: 46133 | Y8: 1 | Z8: 8 | AA8: 31 | AB8: 40
A9: Mar | B9: 7 | D9: 41 | E9: 48 | L9: 46136 | M9: 17 | O9: Execution ready | P9: 341 | Q9: 341 | T9: Mar | U9: 48 | X9: 46134 | Y9: 7 | Z9: 5 | AA9: 31 | AB9: 43
A10: Apr | B10: 29 | D10: 62 | E10: 91 | L10: Grand Total | M10: 190 | O10: LCM Verification | P10: 264 | Q10: 264 | T10: Apr | U10: 91 | X10: 46135 | Y10: 1 | Z10: 10 | AA10: 29 | AB10: 40
A11: May | B11: 47 | D11: 107 | E11: 154 | O11: MM updates | P11: 521 | Q11: 521 | T11: May | U11: 154 | X11: 46136 | Y11: 2 | Z11: 2 | AA11: 13 | AB11: 17
A12: Jun | B12: 24 | D12: 187 | E12: 211 | O12: Plant extension | P12: 41 | Q12: 41 | T12: Jun | U12: 211 | X12: Grand Total | Y12: 16 | Z12: 27 | AA12: 147 | AB12: 190
A13: Jul | B13: 64 | D13: 202 | E13: 266 | O13: Quality CR | P13: 90 | Q13: 90 | T13: Jul | U13: 266
A14: Aug | B14: 50 | D14: 202 | E14: 252 | O14: Grand Total | P14: 1806 | Q14: 1806 | T14: Aug | U14: 252
A15: Sep | B15: 74 | D15: 261 | E15: 335 | T15: Sep | U15: 335
A16: Oct | B16: 74 | D16: 281 | E16: 355 | T16: Oct | U16: 355
A17: Nov | B17: 76 | D17: 194 | E17: 270 | T17: Nov | U17: 270
A18: Dec | B18: 63 | D18: 211 | E18: 274 | T18: Dec | U18: 274
A19: 2026 | T19: 2026
A20: Jan | B20: 71 | C20: 31 | D20: 310 | E20: 412 | T20: Jan | U20: 412
A21: Feb | B21: 70 | C21: 48 | D21: 334 | E21: 452 | T21: Feb | U21: 452
A22: Mar | B22: 89 | C22: 66 | D22: 362 | E22: 517 | T22: Mar | U22: 517
A23: Apr | B23: 56 | C23: 48 | D23: 362 | E23: 466 | T23: Apr | U23: 466
A24: Grand Total | B24: 795 | C24: 193 | D24: 3222 | E24: 4210 | T24: Grand Total | U24: 4210

Sheet Total
A1: Change Request | B1: Description | C1: CR type | D1: Process | E1: WF type | F1: Date completed | G1: Month | H1: Total Month | I1: Monthly CRs | J1: Average
A2: 259078 | B2: Update related to Workflow 24761 | C2: MDG | D2: MM updates | E2: MDG CR | F2: 45631 | G2: =TEXT(F2,"mmm -YYYY") -> Dec -2024 | H2: Dec -2024 | I2: =COUNTIF(G:G,H2) -> 10 | J2: =AVERAGE($I$2:I38) -> 247.64706 | K2: =IF(AND(MONTH(F2)=MONTH(TODAY()), YEAR(F2)=YEAR(TODAY())), D2, "") | L2: {=_xlfn.UNIQUE(C:C)} -> CR type
A3: 259159 | B3: ERP- B631_Update Min Lot Size | C3: MDG | D3: MM updates | E3: MDG CR | F3: 45631 | G3: =TEXT(F3,"mmm -YYYY") -> Dec -2024 | H3: Jan -2025 | I3: =COUNTIF(G:G,H3) -> 42 | J3: =AVERAGE($I$2:I39) -> 247.64706 | L3: MDG
A4: 259160 | B4: Update Cross Material Status for Workflow 24742 | C4: MDG | D4: Deployment | E4: P30 | F4: 45631 | G4: =TEXT(F4,"mmm -YYYY") -> Dec -2024 | H4: Feb -2025 | I4: =COUNTIF(G:G,H4) -> 55 | J4: =AVERAGE($I$2:I40) -> 247.64706 | L4: Make
A5: 259388 | B5: Update Cross Material Status for Workflow 24741 | C5: MDG | D5: Deployment | E5: P30 | F5: 45632 | G5: =TEXT(F5,"mmm -YYYY") -> Dec -2024 | H5: Mar -2025 | I5: =COUNTIF(G:G,H5) -> 48 | J5: =AVERAGE($I$2:I41) -> 247.64706 | L5: Mass
A6: 259389 | B6: Update Cross Material Status for Workflow 24743 | C6: MDG | D6: Deployment | E6: P30 | F6: 45632 | G6: =TEXT(F6,"mmm -YYYY") -> Dec -2024 | H6: Apr -2025 | I6: =COUNTIF(G:G,H6) -> 91 | J6: =AVERAGE($I$2:I42) -> 247.64706 | L6: 0
A7: 263894 | B7: CR900001830_ Update MRP controller | C7: MDG | D7: MM updates | E7: MDG CR | F7: 45635 | G7: =TEXT(F7,"mmm -YYYY") -> Dec -2024 | H7: May -2025 | I7: =COUNTIF(G:G,H7) -> 154 | J7: =AVERAGE($I$2:I43) -> 247.64706
A8: 266577 | B8: Update MM fields in code creation | C8: MDG | D8: MM updates | E8: MDG CR | F8: 45638 | G8: =TEXT(F8,"mmm -YYYY") -> Dec -2024 | H8: Jun -2025 | I8: =COUNTIF(G:G,H8) -> 211 | J8: =AVERAGE($I$2:I44) -> 247.64706
A9: 272445 | B9: update of Sales Text in ES (in addition to EN) | C9: MDG | D9: MM updates | E9: MDG CR | F9: 45638 | G9: =TEXT(F9,"mmm -YYYY") -> Dec -2024 | H9: Jul -2025 | I9: =COUNTIF(G:G,H9) -> 266 | J9: =AVERAGE($I$2:I45) -> 247.64706
A10: 272491 | B10: update of Sales Text in EN (in addition to ES) | C10: MDG | D10: MM updates | E10: MDG CR | F10: 45638 | G10: =TEXT(F10,"mmm -YYYY") -> Dec -2024 | H10: Aug -2025 | I10: =COUNTIF(G:G,H10) -> 252 | J10: =AVERAGE($I$2:I46) -> 247.64706
A11: 273410 | B11: remove DChain-spec. status value Y4 | C11: MDG | D11: MM updates | E11: MDG CR | F11: 45638 | G11: =TEXT(F11,"mmm -YYYY") -> Dec -2024 | H11: Sep -2025 | I11: =COUNTIF(G:G,H11) -> 335 | J11: =AVERAGE($I$2:I47) -> 247.64706
A12: 315448 | B12: Updates related to P30 WF 24860 | C12: MDG | D12: Deployment | E12: P30 | F12: 45663 | G12: =TEXT(F12,"mmm -YYYY") -> Jan -2025 | H12: Oct- 2025 | I12: =COUNTIF(G:G,H12) -> 355 | J12: =AVERAGE($I$2:I48) -> 247.64706
A13: 315643 | B13: Enhance MRP Data WF 24857 | C13: MDG | D13: Deployment | E13: P30 | F13: 45663 | G13: =TEXT(F13,"mmm -YYYY") -> Jan -2025 | H13: Nov-2025 | I13: =COUNTIF(G:G,H13) -> 270 | J13: =AVERAGE($I$2:I49) -> 247.64706
A14: 316910 | B14: Data transfer to P30 for WF 24859 | C14: MDG | D14: Deployment | E14: P30 | F14: 45664 | G14: =TEXT(F14,"mmm -YYYY") -> Jan -2025 | H14: Dec-2025 | I14: =COUNTIF(G:G,H14) -> 274 | J14: =AVERAGE($I$2:I50) -> 247.64706
A15: 316944 | B15: Enhance MRP Data WF 24859 | C15: MDG | D15: Deployment | E15: P30 | F15: 45664 | G15: =TEXT(F15,"mmm -YYYY") -> Jan -2025 | H15: Jan-2026 | I15: =COUNTIF(G:G,H15) -> 412 | J15: =AVERAGE($I$2:I51) -> 247.64706
A16: 317159 | B16: WF 900005903 - New FIN material | C16: MDG | D16: Deployment | E16: LCM WF | F16: 45665 | G16: =TEXT(F16,"mmm -YYYY") -> Jan -2025 | H16: Feb -2026 | I16: =COUNTIF(G:G,H16) -> 452 | J16: =AVERAGE($I$2:I52) -> 247.64706
A17: 317124 | B17: WF 900005902 - New FIN material | C17: MDG | D17: Deployment | E17: LCM WF | F17: 45666 | G17: =TEXT(F17,"mmm -YYYY") -> Jan -2025 | H17: Mar-2026 | I17: =COUNTIF(G:G,H17) -> 517 | J17: =AVERAGE($I$2:I53) -> 247.64706
A18: 322183 | B18: Update Gross wt_WF 24891 | C18: MDG | D18: MM updates | E18: MDG CR | F18: 45667 | G18: =TEXT(F18,"mmm -YYYY") -> Jan -2025 | H18: Apr-2026 | I18: =COUNTIF(G:G,H18) -> 466 | J18: =AVERAGE($I$2:I54) -> 247.64706
A19: 322186 | B19: Update MRP controller_WF24890 | C19: MDG | D19: MM updates | E19: MDG CR | F19: 45667 | G19: =TEXT(F19,"mmm -YYYY") -> Jan -2025
A20: 266131 | B20: WF 900005843 - New FIN material | C20: MDG | D20: Deployment | E20: LCM WF | F20: 45670 | G20: =TEXT(F20,"mmm -YYYY") -> Jan -2025
A21: 295544 | B21: WF 900005892 - New FIN material | C21: MDG | D21: Deployment | E21: LCM WF | F21: 45672 | G21: =TEXT(F21,"mmm -YYYY") -> Jan -2025
A22: 326568 | B22: add OMP class | C22: MDG | D22: MM updates | E22: MDG CR | F22: 45672 | G22: =TEXT(F22,"mmm -YYYY") -> Jan -2025
A23: 326752 | B23: Update CoO, RoO | C23: MDG | D23: MM updates | E23: MDG CR | F23: 45672 | G23: =TEXT(F23,"mmm -YYYY") -> Jan -2025
A24: 326754 | B24: Update AUoM | C24: MDG | D24: MM updates | E24: MDG CR | F24: 45672 | G24: =TEXT(F24,"mmm -YYYY") -> Jan -2025
A25: 326755 | B25: Update CoO,RoO | C25: MDG | D25: MM updates | E25: MDG CR | F25: 45672 | G25: =TEXT(F25,"mmm -YYYY") -> Jan -2025
A26: 327307 | B26: Update AUoM in A411 for code creation | C26: MDG | D26: MM updates | E26: MDG CR | F26: 45673 | G26: =TEXT(F26,"mmm -YYYY") -> Jan -2025
A27: 327320 | B27: Update AUoM for A411 - WF 24872 | C27: MDG | D27: MM updates | E27: MDG CR | F27: 45673 | G27: =TEXT(F27,"mmm -YYYY") -> Jan -2025
A28: 327380 | B28: Updates to A411 - WF 24872 | C28: MDG | D28: Deployment | E28: P30 | F28: 45673 | G28: =TEXT(F28,"mmm -YYYY") -> Jan -2025
A29: 327746 | B29: TOLL_ZRAW_Update GMP_P30_Plant 1001 | C29: MDG | D29: Execution ready | E29: MDG CR | F29: 45673 | G29: =TEXT(F29,"mmm -YYYY") -> Jan -2025
A30: 327780 | B30: Push to P30 WF 24867 | C30: MDG | D30: Deployment | E30: P30 | F30: 45673 | G30: =TEXT(F30,"mmm -YYYY") -> Jan -2025
... A104: 485619 | B104: Data push to P30 for plant 1001 & 2670 CR 481673 | C104: MDG | D104: Deployment | E104: P30 | F104: 45715 | G104: =TEXT(F104,"mmm -YYYY") -> Feb -2025
A105: 482213A | B105: A411 BoM & Recipe creation | C105: Make | D105: Make Deployment | E105: Mass upload | F105: 45715 | G105: =TEXT(F105,"mmm -YYYY") -> Feb -2025
A106: 481022 | B106: AFF_ZFIN_Execution-Ready_P30_Plant 2670 | C106: MDG | D106: Execution ready | E106: MDG CR | F106: 45716 | G106: =TEXT(F106,"mmm -YYYY") -> Feb -2025
A107: 486744 | B107: Enhance MRP Data for plant A411 CR 481673 | C107: MDG | D107: Deployment | E107: P30 | F107: 45716 | G107: =TEXT(F107,"mmm -YYYY") -> Feb -2025
A108: 486746 | B108: Enhance Client datat for CR 481673 | C108: MDG | D108: Deployment | E108: P30 | F108: 45716 | G108: =TEXT(F108,"mmm -YYYY") -> Feb -2025
A109: 485752A | B109: A411 BoM & Recipe creation | C109: Make | D109: Make Deployment | E109: Mass upload | F109: 45719 | G109: =TEXT(F109,"mmm -YYYY") -> Mar -2025
A110: 500445 | B110: Update MM - WF 25020 | C110: MDG | D110: MM updates | E110: MDG CR | F110: 45720 | G110: =TEXT(F110,"mmm -YYYY") -> Mar -2025
A111: 480291 | B111: DEPLOY SEMP CR477016 | C111: MDG | D111: Deployment | E111: LCM WF | F111: 45721 | G111: =TEXT(F111,"mmm -YYYY") -> Mar -2025
A112: 482102 | B112: WF 900005967 - New FIN material | C112: MDG | D112: Deployment | E112: LCM WF | F112: 45722 | G112: =TEXT(F112,"mmm -YYYY") -> Mar -2025
A113: 482105 | B113: WF 900005966 - New FIN material | C113: MDG | D113: Deployment | E113: LCM WF | F113: 45722 | G113: =TEXT(F113,"mmm -YYYY") -> Mar -2025
A114: 510127 | B114: Data Push to P30 for CR 490397 | C114: MDG | D114: Deployment | E114: P30 | F114: 45722 | G114: =TEXT(F114,"mmm -YYYY") -> Mar -2025
A115: 489701A | B115: A411 BoM & Recipe creation | C115: Make | D115: Make Deployment | E115: Mass upload | F115: 45723 | G115: =TEXT(F115,"mmm -YYYY") -> Mar -2025
A116: 481912 | B116: TOLL_ZFIN_Ready for Execution_P30 (FINP)_Plant 1001 | C116: MDG | D116: Execution ready | E116: MDG CR | F116: 45726 | G116: =TEXT(F116,"mmm -YYYY") -> Mar -2025
A117: 506660 | B117: AFF_ZFIN_Affiliate_Update_P30_Plant 2671 | C117: MDG | D117: Execution ready | E117: MDG CR | F117: 45726 | G117: =TEXT(F117,"mmm -YYYY") -> Mar -2025
A118: 541363 | B118: Enhance data for plant A411 WF 25036 | C118: MDG | D118: Deployment | E118: P30 | F118: 45726 | G118: =TEXT(F118,"mmm -YYYY") -> Mar -2025
A119: 541654 | B119: Enhance data for A411 for CR481666 | C119: MDG | D119: Deployment | E119: P30 | F119: 45726 | G119: =TEXT(F119,"mmm -YYYY") -> Mar -2025
A120: 541915 | B120: Enhance data for A411 for CR481666 | C120: MDG | D120: Deployment | E120: P30 | F120: 45726 | G120: =TEXT(F120,"mmm -YYYY") -> Mar -2025
A121: 541281 | B121: Data Push to P30 WF 25036 | C121: MDG | D121: Deployment | E121: P30 | F121: 45726 | G121: =TEXT(F121,"mmm -YYYY") -> Mar -2025
A122: 541283 | B122: Enhance data for plant A411 WF 25036 | C122: MDG | D122: Deployment | E122: P30 | F122: 45726 | G122: =TEXT(F122,"mmm -YYYY") -> Mar -2025
A123: 541285 | B123: Enhance data for A411 WF 25036 | C123: MDG | D123: Deployment | E123: P30 | F123: 45726 | G123: =TEXT(F123,"mmm -YYYY") -> Mar -2025
A124: 546370 | B124: Data Push to P30 for CR 482190 LCM | C124: MDG | D124: Deployment | E124: P30 | F124: 45727 | G124: =TEXT(F124,"mmm -YYYY") -> Mar -2025
A125: 546427 | B125: Push to P30 WF 25040 | C125: MDG | D125: Deployment | E125: P30 | F125: 45727 | G125: =TEXT(F125,"mmm -YYYY") -> Mar -2025
A126: 547147 | B126: Push data to P30 CR 483623 LCM | C126: MDG | D126: Deployment | E126: P30 | F126: 45727 | G126: =TEXT(F126,"mmm -YYYY") -> Mar -2025
A127: 550624 | B127: Planning ready for CR 483624 | C127: MDG | D127: Deployment | E127: LCM WF | F127: 45728 | G127: =TEXT(F127,"mmm -YYYY") -> Mar -2025
... A144: 546847 | B144: DEPLOY FINP CR546735 | C144: MDG | D144: Deployment | E144: LCM WF | F144: 45738 | G144: =TEXT(F144,"mmm -YYYY") -> Mar -2025
A145: 486899A | B145: A411 BoM & Recipe creation | C145: Make | D145: Make Deployment | E145: Mass upload | F145: 45738 | G145: =TEXT(F145,"mmm -YYYY") -> Mar -2025
A146: 615114 | B146: CMO_ZSEM_Non-GMP_P30_Plant 1001_Update CoO | C146: MDG | D146: MM updates | E146: MDG CR | F146: 45741 | G146: =TEXT(F146,"mmm -YYYY") -> Mar -2025
A147: 619393 | B147: TSL update | C147: MDG | D147: MM updates | E147: MDG CR | F147: 45741 | G147: =TEXT(F147,"mmm -YYYY") -> Mar -2025
A148: 618132 | B148: Data push to P30 CR 593504 LCM | C148: MDG | D148: Deployment | E148: P30 | F148: 45741 | G148: =TEXT(F148,"mmm -YYYY") -> Mar -2025
A149: 623322 | B149: Material master update | C149: MDG | D149: MM updates | E149: MDG CR | F149: 45742 | G149: =TEXT(F149,"mmm -YYYY") -> Mar -2025
A150: 482190 | B150: DEPLOY FINP CR482169 | C150: MDG | D150: Deployment | E150: LCM WF | F150: 45743 | G150: =TEXT(F150,"mmm -YYYY") -> Mar -2025
A151: 483623 | B151: DEPLOY FINP CR482213 | C151: MDG | D151: Deployment | E151: LCM WF | F151: 45743 | G151: =TEXT(F151,"mmm -YYYY") -> Mar -2025
A152: 615804 | B152: AFF_ZFIN_Execution-Ready_P30_Plant 2672_Costing update | C152: MDG | D152: Execution ready | E152: MDG CR | F152: 45743 | G152: =TEXT(F152,"mmm -YYYY") -> Mar -2025
A153: 626044 | B153: Planning ready MDG CR 593626 | C153: MDG | D153: Deployment | E153: LCM WF | F153: 45743 | G153: =TEXT(F153,"mmm -YYYY") -> Mar -2025
A154: 626717 | B154: TSL update from ALPIN | C154: MDG | D154: MM updates | E154: MDG CR | F154: 45743 | G154: =TEXT(F154,"mmm -YYYY") -> Mar -2025
A155: 626901 | B155: TSL update from ALPIN | C155: MDG | D155: MM updates | E155: MDG CR | F155: 45743 | G155: =TEXT(F155,"mmm -YYYY") -> Mar -2025
A156: 482190A | B156: A411 BoM & Recipe creation | C156: Make | D156: Make Deployment | E156: Mass upload | F156: 45743 | G156: =TEXT(F156,"mmm -YYYY") -> Mar -2025
A157: 599903 | B157: DEPLOY FINP CR593617 | C157: MDG | D157: Deployment | E157: LCM WF | F157: 45748 | G157: =TEXT(F157,"mmm -YYYY") -> Apr -2025
A158: 600044 | B158: DEPLOY FINP CR592960 | C158: MDG | D158: Deployment | E158: LCM WF | F158: 45748 | G158: =TEXT(F158,"mmm -YYYY") -> Apr -2025
A159: 614202 | B159: DEPLOY FINP CR603233 | C159: MDG | D159: Deployment | E159: LCM WF | F159: 45748 | G159: =TEXT(F159,"mmm -YYYY") -> Apr -2025
A160: 644744 | B160: Planning ready CR 614848 | C160: MDG | D160: Deployment | E160: LCM WF | F160: 45748 | G160: =TEXT(F160,"mmm -YYYY") -> Apr -2025
A161: 644914 | B161: Planning ready CR 614848 | C161: MDG | D161: Deployment | E161: LCM WF | F161: 45748 | G161: =TEXT(F161,"mmm -YYYY") -> Apr -2025
A162: 645366 | B162: Plant status update for A513 | C162: MDG | D162: MM updates | E162: MDG CR | F162: 45748 | G162: =TEXT(F162,"mmm -YYYY") -> Apr -2025
A163: 516576 | B163: DEPLOY ZFIN CR489701 | C163: MDG | D163: Deployment | E163: LCM WF | F163: 45749 | G163: =TEXT(F163,"mmm -YYYY") -> Apr -2025
A164: 614848 | B164: DEPLOY FINP CR603614 | C164: MDG | D164: Deployment | E164: LCM WF | F164: 45749 | G164: =TEXT(F164,"mmm -YYYY") -> Apr -2025
A165: 649730 | B165: Updates related to WF 25077 | C165: MDG | D165: Deployment | E165: P30 | F165: 45749 | G165: =TEXT(F165,"mmm -YYYY") -> Apr -2025
A166: 649868 | B166: Updates related to WF 600045 | C166: MDG | D166: Deployment | E166: P30 | F166: 45749 | G166: =TEXT(F166,"mmm -YYYY") -> Apr -2025
A167: 100001884 | B167: MDG CR 619165 | C167: Make | D167: Make Verification | E167: R10 | F167: 45749 | G167: =TEXT(F167,"mmm -YYYY") -> Apr -2025
A168: 100001883 | B168: MDG CR 619165 | C168: Make | D168: Make Verification | E168: R10 | F168: 45749 | G168: =TEXT(F168,"mmm -YYYY") -> Apr -2025
... A170: 660683 | B170: Updates related to WF 599971 | C170: MDG | D170: Deployment | E170: P30 | F170: 45751 | G170: =TEXT(F170,"mmm -YYYY") -> Apr -2025
A171: 593504A | B171: A411 BoM & Recipe creation | C171: Make | D171: Make Deployment | E171: Mass upload | F171: 45751 | G171: =TEXT(F171,"mmm -YYYY") -> Apr -2025
A172: 500359 | B172: DEPLOY FIN CR485752 | C172: MDG | D172: Deployment | E172: LCM WF | F172: 45754 | G172: =TEXT(F172,"mmm -YYYY") -> Apr -2025
A173: 593539 | B173: DEPLOY FINP CR593454 | C173: MDG | D173: Deployment | E173: LCM WF | F173: 45754 | G173: =TEXT(F173,"mmm -YYYY") -> Apr -2025
A174: 607656 | B174: DEPLOY FINP CR602795 | C174: MDG | D174: Deployment | E174: LCM WF | F174: 45754 | G174: =TEXT(F174,"mmm -YYYY") -> Apr -2025
A175: 607657 | B175: DEPLOY FINP CR602857 | C175: MDG | D175: Deployment | E175: LCM WF | F175: 45754 | G175: =TEXT(F175,"mmm -YYYY") -> Apr -2025
A176: 619386 | B176: WF 900006026 - New FIN material | C176: MDG | D176: Deployment | E176: LCM WF | F176: 45754 | G176: =TEXT(F176,"mmm -YYYY") -> Apr -2025
A177: 593539A | B177: A411 BoM & Recipe creation | C177: Make | D177: Make Deployment | E177: Mass upload | F177: 45754 | G177: =TEXT(F177,"mmm -YYYY") -> Apr -2025
A178: 100001930 | B178: A511 Create DPI Tron 50MG CPMF | C178: Make | D178: Make Deployment | E178: G15 | F178: 45754 | G178: =TEXT(F178,"mmm -YYYY") -> Apr -2025
A179: 100001901 | B179: A511 Update DPI Ocre SC HC CPMF | C179: Make | D179: Make Deployment | E179: G15 | F179: 45754 | G179: =TEXT(F179,"mmm -YYYY") -> Apr -2025
A180: 100001912 | B180: MDG CR 619430 | C180: Make | D180: Make Verification | E180: R10 | F180: 45754 | G180: =TEXT(F180,"mmm -YYYY") -> Apr -2025
A181: 619439 | B181: WF 900006026 - New FIN material | C181: MDG | D181: Deployment | E181: LCM WF | F181: 45755 | G181: =TEXT(F181,"mmm -YYYY") -> Apr -2025
A182: 619525 | B182: WF 900006026 - New FIN material | C182: MDG | D182: Deployment | E182: LCM WF | F182: 45755 | G182: =TEXT(F182,"mmm -YYYY") -> Apr -2025
A183: 626235 | B183: WF 900006041 - New FIN material | C183: MDG | D183: Deployment | E183: LCM WF | F183: 45755 | G183: =TEXT(F183,"mmm -YYYY") -> Apr -2025
A184: 626306 | B184: WF 900006041 - New FIN material | C184: MDG | D184: Deployment | E184: LCM WF | F184: 45755 | G184: =TEXT(F184,"mmm -YYYY") -> Apr -2025
A185: 626375 | B185: WF 900006041 - New FIN material | C185: MDG | D185: Deployment | E185: LCM WF | F185: 45755 | G185: =TEXT(F185,"mmm -YYYY") -> Apr -2025
A186: 626792 | B186: WF 900006041 - New FIN material | C186: MDG | D186: Deployment | E186: LCM WF | F186: 45755 | G186: =TEXT(F186,"mmm -YYYY") -> Apr -2025
A187: 100001869 | B187: A511 Update Mosunetuzumab 1MG CPMF | C187: Make | D187: Make Deployment | E187: G15 | F187: 45755 | G187: =TEXT(F187,"mmm -YYYY") -> Apr -2025
A188: 100001921 | B188: A511 Update DPI GLofit 2.5MG CPMF | C188: Make | D188: Make Deployment | E188: G15 | F188: 45755 | G188: =TEXT(F188,"mmm -YYYY") -> Apr -2025
A189: 683097 | B189: Updates Related to WF 25169 | C189: MDG | D189: Deployment | E189: P30 | F189: 45756 | G189: =TEXT(F189,"mmm -YYYY") -> Apr -2025
... A342: 900003188 | B342: israel ean category update | C342: MDG | D342: MM updates | E342: CR 999 | F342: 45799 | G342: =TEXT(F342,"mmm -YYYY") -> May -2025
...

Sheet Summary
A1: Date completed | B1: No.of WFs | C1: Make CRs | D1: MDG CRs | E1: Mass CRs
A2: 45631 | B2: =COUNTIFS(Total!F:F, A2, Total!A:A, "<>") -> 3 | C2: =COUNTIFS(Total!C:C,$N$4,Total!F:F, A2, Total!A:A, "<>") -> 0 | D2: =COUNTIFS(Total!C:C,$N$3,Total!F:F, A2, Total!A:A, "<>") -> 3 | E2: =COUNTIFS(Total!C:C,$N$5,Total!F:F, A2, Total!A:A, "<>") -> 0 | N2: CR type
A3: 45632 | B3: =COUNTIFS(Total!F:F, A3, Total!A:A, "<>") -> 2 | C3: =COUNTIFS(Total!C:C,$N$4,Total!F:F, A3, Total!A:A, "<>") -> 0 | D3: =COUNTIFS(Total!C:C,$N$3,Total!F:F, A3, Total!A:A, "<>") -> 2 | E3: =COUNTIFS(Total!C:C,$N$5,Total!F:F, A3, Total!A:A, "<>") -> 0 | N3: MDG | T3: Dec -2024
A4: 45635 | B4: =COUNTIFS(Total!F:F, A4, Total!A:A, "<>") -> 1 | C4: =COUNTIFS(Total!C:C,$N$4,Total!F:F, A4, Total!A:A, "<>") -> 0 | D4: =COUNTIFS(Total!C:C,$N$3,Total!F:F, A4, Total!A:A, "<>") -> 1 | E4: =COUNTIFS(Total!C:C,$N$5,Total!F:F, A4, Total!A:A, "<>") -> 0 | N4: Make | T4: Jan -2025
A5: 45638 | B5: =COUNTIFS(Total!F:F, A5, Total!A:A, "<>") -> 4 | C5: =COUNTIFS(Total!C:C,$N$4,Total!F:F, A5, Total!A:A, "<>") -> 0 | D5: =COUNTIFS(Total!C:C,$N$3,Total!F:F, A5, Total!A:A, "<>") -> 4 | E5: =COUNTIFS(Total!C:C,$N$5,Total!F:F, A5, Total!A:A, "<>") -> 0 | N5: Mass | T5: Feb -2025
A6: 45663 | B6: =COUNTIFS(Total!F:F, A6, Total!A:A, "<>") -> 2 | C6: =COUNTIFS(Total!C:C,$N$4,Total!F:F, A6, Total!A:A, "<>") -> 0 | D6: =COUNTIFS(Total!C:C,$N$3,Total!F:F, A6, Total!A:A, "<>") -> 2 | E6: =COUNTIFS(Total!C:C,$N$5,Total!F:F, A6, Total!A:A, "<>") -> 0 | T6: Mar -2025
A7: 45664 | B7: =COUNTIFS(Total!F:F, A7, Total!A:A, "<>") -> 2 | C7: =COUNTIFS(Total!C:C,$N$4,Total!F:F, A7, Total!A:A, "<>") -> 0 | D7: =COUNTIFS(Total!C:C,$N$3,Total!F:F, A7, Total!A:A, "<>") -> 2 | E7: =COUNTIFS(Total!C:C,$N$5,Total!F:F, A7, Total!A:A, "<>") -> 0 | T7: Apr -2025
A8: 45665 | B8: =COUNTIFS(Total!F:F, A8, Total!A:A, "<>") -> 1 | C8: =COUNTIFS(Total!C:C,$N$4,Total!F:F, A8, Total!A:A, "<>") -> 0 | D8: =COUNTIFS(Total!C:C,$N$3,Total!F:F, A8, Total!A:A, "<>") -> 1 | E8: =COUNTIFS(Total!C:C,$N$5,Total!F:F, A8, Total!A:A, "<>") -> 0 | T8: May -2025
A9: 45666 | B9: =COUNTIFS(Total!F:F, A9, Total!A:A, "<>") -> 1 | C9: =COUNTIFS(Total!C:C,$N$4,Total!F:F, A9, Total!A:A, "<>") -> 0 | D9: =COUNTIFS(Total!C:C,$N$3,Total!F:F, A9, Total!A:A, "<>") -> 1 | E9: =COUNTIFS(Total!C:C,$N$5,Total!F:F, A9, Total!A:A, "<>") -> 0 | T9: Jun -2025
A10: 45667 | B10: =COUNTIFS(Total!F:F, A10, Total!A:A, "<>") -> 2 | C10: =COUNTIFS(Total!C:C,$N$4,Total!F:F, A10, Total!A:A, "<>") -> 0 | D10: =COUNTIFS(Total!C:C,$N$3,Total!F:F, A10, Total!A:A, "<>") -> 2 | E10: =COUNTIFS(Total!C:C,$N$5,Total!F:F, A10, Total!A:A, "<>") -> 0 | T10: Jul -2025
A11: 45670 | B11: =COUNTIFS(Total!F:F, A11, Total!A:A, "<>") -> 1 | C11: =COUNTIFS(Total!C:C,$N$4,Total!F:F, A11, Total!A:A, "<>") -> 0 | D11: =COUNTIFS(Total!C:C,$N$3,Total!F:F, A11, Total!A:A, "<>") -> 1 | E11: =COUNTIFS(Total!C:C,$N$5,Total!F:F, A11, Total!A:A, "<>") -> 0 | T11: Aug -2025
A12: 45672 | B12: =COUNTIFS(Total!F:F, A12, Total!A:A, "<>") -> 5 | C12: =COUNTIFS(Total!C:C,$N$4,Total!F:F, A12, Total!A:A, "<>") -> 0 | D12: =COUNTIFS(Total!C:C,$N$3,Total!F:F, A12, Total!A:A, "<>") -> 5 | E12: =COUNTIFS(Total!C:C,$N$5,Total!F:F, A12, Total!A:A, "<>") -> 0 | T12: Sep -2025
A13: 45673 | B13: =COUNTIFS(Total!F:F, A13, Total!A:A, "<>") -> 5 | C13: =COUNTIFS(Total!C:C,$N$4,Total!F:F, A13, Total!A:A, "<>") -> 0 | D13: =COUNTIFS(Total!C:C,$N$3,Total!F:F, A13, Total!A:A, "<>") -> 5 | E13: =COUNTIFS(Total!C:C,$N$5,Total!F:F, A13, Total!A:A, "<>") -> 0
A14: 45674 | B14: =COUNTIFS(Total!F:F, A14, Total!A:A, "<>") -> 2 | C14: =COUNTIFS(Total!C:C,$N$4,Total!F:F, A14, Total!A:A, "<>") -> 0 | D14: =COUNTIFS(Total!C:C,$N$3,Total!F:F, A14, Total!A:A, "<>") -> 2 | E14: =COUNTIFS(Total!C:C,$N$5,Total!F:F, A14, Total!A:A, "<>") -> 0
A15: 45677 | B15: =COUNTIFS(Total!F:F, A15, Total!A:A, "<>") -> 1 | C15: =COUNTIFS(Total!C:C,$N$4,Total!F:F, A15, Total!A:A, "<>") -> 0 | D15: =COUNTIFS(Total!C:C,$N$3,Total!F:F, A15, Total!A:A, "<>") -> 1 | E15: =COUNTIFS(Total!C:C,$N$5,Total!F:F, A15, Total!A:A, "<>") -> 0
A16: 45679 | B16: =COUNTIFS(Total!F:F, A16, Total!A:A, "<>") -> 4 | C16: =COUNTIFS(Total!C:C,$N$4,Total!F:F, A16, Total!A:A, "<>") -> 0 | D16: =COUNTIFS(Total!C:C,$N$3,Total!F:F, A16, Total!A:A, "<>") -> 4 | E16: =COUNTIFS(Total!C:C,$N$5,Total!F:F, A16, Total!A:A, "<>") -> 0
A17: 45684 | B17: =COUNTIFS(Total!F:F, A17, Total!A:A, "<>") -> 1 | C17: =COUNTIFS(Total!C:C,$N$4,Total!F:F, A17, Total!A:A, "<>") -> 0 | D17: =COUNTIFS(Total!C:C,$N$3,Total!F:F, A17, Total!A:A, "<>") -> 1 | E17: =COUNTIFS(Total!C:C,$N$5,Total!F:F, A17, Total!A:A, "<>") -> 0
A18: 45685 | B18: =COUNTIFS(Total!F:F, A18, Total!A:A, "<>") -> 4 | C18: =COUNTIFS(Total!C:C,$N$4,Total!F:F, A18, Total!A:A, "<>") -> 0 | D18: =COUNTIFS(Total!C:C,$N$3,Total!F:F, A18, Total!A:A, "<>") -> 4 | E18: =COUNTIFS(Total!C:C,$N$5,Total!F:F, A18, Total!A:A, "<>") -> 0
A19: 45686 | B19: =COUNTIFS(Total!F:F, A19, Total!A:A, "<>") -> 7 | C19: =COUNTIFS(Total!C:C,$N$4,Total!F:F, A19, Total!A:A, "<>") -> 0 | D19: =COUNTIFS(Total!C:C,$N$3,Total!F:F, A19, Total!A:A, "<>") -> 7 | E19: =COUNTIFS(Total!C:C,$N$5,Total!F:F, A19, Total!A:A, "<>") -> 0
A20: 45687 | B20: =COUNTIFS(Total!F:F, A20, Total!A:A, "<>") -> 4 | C20: =COUNTIFS(Total!C:C,$N$4,Total!F:F, A20, Total!A:A, "<>") -> 0 | D20: =COUNTIFS(Total!C:C,$N$3,Total!F:F, A20, Total!A:A, "<>") -> 4 | E20: =COUNTIFS(Total!C:C,$N$5,Total!F:F, A20, Total!A:A, "<>") -> 0
A21: 45691 | B21: =COUNTIFS(Total!F:F, A21, Total!A:A, "<>") -> 1 | C21: =COUNTIFS(Total!C:C,$N$4,Total!F:F, A21, Total!A:A, "<>") -> 0 | D21: =COUNTIFS(Total!C:C,$N$3,Total!F:F, A21, Total!A:A, "<>") -> 1 | E21: =COUNTIFS(Total!C:C,$N$5,Total!F:F, A21, Total!A:A, "<>") -> 0
A22: 45692 | B22: =COUNTIFS(Total!F:F, A22, Total!A:A, "<>") -> 4 | C22: =COUNTIFS(Total!C:C,$N$4,Total!F:F, A22, Total!A:A, "<>") -> 0 | D22: =COUNTIFS(Total!C:C,$N$3,Total!F:F, A22, Total!A:A, "<>") -> 4 | E22: =COUNTIFS(Total!C:C,$N$5,Total!F:F, A22, Total!A:A, "<>") -> 0
A23: 45693 | B23: =COUNTIFS(Total!F:F, A23, Total!A:A, "<>") -> 7 | C23: =COUNTIFS(Total!C:C,$N$4,Total!F:F, A23, Total!A:A, "<>") -> 0 | D23: =COUNTIFS(Total!C:C,$N$3,Total!F:F, A23, Total!A:A, "<>") -> 7 | E23: =COUNTIFS(Total!C:C,$N$5,Total!F:F, A23, Total!A:A, "<>") -> 0
A24: 45694 | B24: =COUNTIFS(Total!F:F, A24, Total!A:A, "<>") -> 6 | C24: =COUNTIFS(Total!C:C,$N$4,Total!F:F, A24, Total!A:A, "<>") -> 0 | D24: =COUNTIFS(Total!C:C,$N$3,Total!F:F, A24, Total!A:A, "<>") -> 6 | E24: =COUNTIFS(Total!C:C,$N$5,Total!F:F, A24, Total!A:A, "<>") -> 0
... A477: 46227 | B477: =COUNTIFS(Total!F:F, A477, Total!A:A, "<>") -> 0 | C477: =COUNTIFS(Total!C:C,$N$4,Total!F:F, A477, Total!A:A, "<>") -> 0 | D477: =COUNTIFS(Total!C:C,$N$3,Total!F:F, A477, Total!A:A, "<>") -> 0 | E477: =COUNTIFS(Total!C:C,$N$5,Total!F:F, A477, Total!A:A, "<>") -> 0
